{"status":"ok","medias":[{"id":299544,"cid":0,"title":"Big Bang","description":"Tras pasar las vacaciones de verano separados, la pandilla se reúne para oir los comentarios del viaje de Sheldon y Amy con la madre de Sheldon, la aventura del árbol de Navidad de Leonard y Penny, y el primer día como padres de Howard y Bernadette.","files":null,"tags_metas":[{"key":"Category","value":"Series"},{"key":"Parental Rating","value":"17"},{"key":"Actors","value":"Cuoco,Kaley|Helberg,Simon|Galecki,Johnny|Parsons,Jim|Nayyar,Kunal"},{"key":"Country","value":"Estados Unidos"},{"key":"Director","value":"Cendrowski,Mark"},{"key":"Series name","value":"Big Bang"},{"key":"Season Numbers","value":"10"},{"key":"Genre_Tag","value":"Series Extranjeras|Comedia"},{"key":"Main cast","value":"Cuoco,Kaley|Helberg,Simon|Galecki,Johnny|Parsons,Jim|Nayyar,Kunal"},{"key":"Series ID","value":"60877"},{"key":"Target","value":"DCTI384|STB"},{"key":"SeriesId ","value":"60877"},{"key":"Summary short","value":"Tras pasar las vacaciones de verano separados, la pandilla se reúne para hablar sobre ellas: el viaje de Sheldon y Amy con la madre de Sheldon..."},{"key":"External ONO ID","value":"TUBR0000000000001921"},{"key":"Genre","value":"Series Extranjeras/Comedia"},{"key":"Actors display","value":"Johnny Galecki, Jim Parsons, Kaley Cuoco, Simon Helberg, Kunal Nayyar"},{"key":"Director display","value":"Mark Cendrowski"},{"key":"Year","value":2016},{"key":"Release year","value":2016},{"key":"Suggestion","value":false},{"key":"IsDeepLink","value":false}],"total_seasons":1,"seasons":[10],"type_name":"series","pictures":{"banner":"http://kal-images.ono.es/app_posters/3f6f36078cbd46238a9a14470e33cf89_920X602.jpg","poster":"http://kal-images.ono.es/app_posters/3f6f36078cbd46238a9a14470e33cf89_286X429.jpg"},"orientation":"2:3"}]}