{"status":"ok","medias":[{"id":304572,"cid":0,"title":"La Princesa Sofía","description":"Tras la boda de su madre con el Rey, Sofía se traslada a vivir a Palacio, donde deberá aprender a ser una princesa.","files":null,"tags_metas":[{"key":"Category","value":"Infantil"},{"key":"Parental Rating","value":"17"},{"key":"Country","value":"Estados Unidos"},{"key":"Series name","value":"La Princesa Sofía"},{"key":"Season Numbers","value":"1|2"},{"key":"Genre_Tag","value":"Series Extranjeras|Infantil"},{"key":"Series ID","value":"148100"},{"key":"Target","value":"DCTI384|STB"},{"key":"SeriesId ","value":"148100"},{"key":"Summary short","value":"Tras la boda de su madre con el Rey, Sofía se traslada a vivir a Palacio, donde deberá aprender a ser una princesa."},{"key":"External ONO ID","value":"DISN0000000000001371"},{"key":"Genre","value":"Series Extranjeras/Infantil"},{"key":"Year","value":2013},{"key":"Release year","value":2013},{"key":"Suggestion","value":false},{"key":"IsDeepLink","value":false}],"total_seasons":2,"seasons":[1,2],"type_name":"series","pictures":{"banner":"http://kal-images.ono.es/app_posters/b4aee2c4b3ca470caf774aec8eded21a_920X602.jpg","poster":"http://kal-images.ono.es/app_posters/b4aee2c4b3ca470caf774aec8eded21a_286X429.jpg"},"orientation":"2:3"}]}